<?xml version='1.0' encoding='utf-8'?>
<QuestDialog xmlns="https://vezel.dev/novadrop/dc/QuestDialog" xmlns:xsi="http://www.w3.org/2001/XMLSchema-instance" xsi:schemaLocation="https://vezel.dev/novadrop/dc/QuestDialog QuestDialog.xsd" huntingZoneId="16" id="34" voiceTypeId="0">
    <Text huntingZoneId="0" id="1" prevId="0" villagerId="0" />
    <Text huntingZoneId="216" id="100" prevId="0" villagerId="1023">
         
        <Page social="0" />
    
    </Text>
    <Text huntingZoneId="216" id="2" prevId="0" villagerId="1023">
         
        <Page social="4">Encontramos rastros de {@LinkCreature:16#2304$$sanguine moppets} e {@LinkCreature:16#2303#vampir jesters}, portanto não são os vampiros. Isso é claramente outra coisa.&lt;BR&gt;&lt;BR&gt;Preciso que você encontre mais pistas.</Page>
    
    </Text>
    <Text huntingZoneId="216" id="3" prevId="2" villagerId="1023">
         
        <Page social="4">Isso não é bom. Quero dizer, não, você fez um bom trabalho, mas essas pedras são... demoníacas. É isso que está acontecendo? Os demônios estão controlando os vampiros? &lt;BR&gt;&lt;BR&gt;Tenho mais coisas para resolver, mas obrigado por encontrá-las.</Page>
    
    </Text>
    <Text huntingZoneId="216" id="4" villagerId="1023">
         
        <Page social="0">Quando você me trouxer mais pistas, terei uma ideia melhor do que está acontecendo.</Page>
    
    </Text>
</QuestDialog>