<?xml version='1.0' encoding='utf-8'?>
<QuestDialog xmlns="https://vezel.dev/novadrop/dc/QuestDialog" xmlns:xsi="http://www.w3.org/2001/XMLSchema-instance" xsi:schemaLocation="https://vezel.dev/novadrop/dc/QuestDialog QuestDialog.xsd" huntingZoneId="6" id="39" voiceTypeId="0">
    <Text huntingZoneId="0" id="1" prevId="0" villagerId="0" />
    <Text huntingZoneId="206" id="100" prevId="0" villagerId="1006">
         
        <Page social="0" />
    
    </Text>
    <Text huntingZoneId="206" id="2" prevId="0" villagerId="1006">
         
        <Page social="5">É bom ver os Gutrends colocados em seu lugar dessa maneira. Mais cedo ou mais tarde, talvez eles finalmente saiam e nos dêem paz.&lt;BR&gt;&lt;BR&gt;Mesmo assim, estamos fazendo um excelente progresso. Crevan, no Acampamento dos Vindicadores, vai querer saber disso.&lt;BR&gt;&lt;BR&gt;Já que você é responsável por grande parte do nosso sucesso, por que não leva você mesmo a mensagem a ele?</Page>
    
    </Text>
    <Text huntingZoneId="206" id="3" prevId="2" villagerId="1021">
         
        <Page social="5">Você fez o Gutrend recuar vários degraus, não foi? Bem, essa é uma notícia maravilhosa.&lt;BR&gt;&lt;BR&gt;Whimnia também vai querer ouvir isso. Por favor, avise-a.</Page>
    
    </Text>
    <Text huntingZoneId="206" id="4" prevId="3" villagerId="1013">
         
        <Page social="5">Oh, essa é uma boa notícia.&lt;BR&gt;&lt;BR&gt;Eu vou anotar. Garanto que vamos tirar proveito disso.</Page>
    
    </Text>
</QuestDialog>