
<StrSheet_Quest xmlns="https://vezel.dev/novadrop/dc/StrSheet_Quest" xmlns:xsi="http://www.w3.org/2001/XMLSchema-instance" xsi:schemaLocation="https://vezel.dev/novadrop/dc/StrSheet_Quest StrSheet_Quest.xsd">
    <String id="4829001" string="Caído, mas não esquecido" />
    <String id="4829002" string="Não podemos simplesmente deixá-los lá fora." />
    <String id="4829003" string="Vejo vocês em Pareseshan, irmãos." />
    <String id="4829004" string="&quot;Descanse bem, meu amigo.&quot;" />
    <String id="4829005" string="&quot;Eu honro seu sacrifício.&quot;" />
    <String id="4829006" string="&quot;Eu o levarei para casa.&quot;" />
    <String id="4829007" string="&quot;Que Kaia o honre&quot;." />
    <String id="4829008" string="Recupere os chifres dos ferreiros mortos." />
    <String id="4829009" string="{@LinkCreature:248#1030}" />
    <String id="4829010" string="Chifre de Amani" />
    <String id="4829011" string="Entregue os chifres a Chatran." />
    <String id="4829012" string="&quot;Fico feliz por ter ajudado.&quot;" />
</StrSheet_Quest>
