
<StrSheet_Quest xmlns="https://vezel.dev/novadrop/dc/StrSheet_Quest" xmlns:xsi="http://www.w3.org/2001/XMLSchema-instance" xsi:schemaLocation="https://vezel.dev/novadrop/dc/StrSheet_Quest StrSheet_Quest.xsd">
    <String id="18105001" string="Pequenos cordeiros perdidos" />
    <String id="18105002" string="&quot;Posso ajudá-lo, se estiver pronto para ir.&quot;" />
    <String id="18105003" string="Fale com o pesquisador preso." />
    <String id="18105004" string="&quot;Você pode contar comigo.&quot;" />
    <String id="18105005" string="Obrigado! Tenho que informar a Hagand que retornei. Você pode ir consolar meu amigo Rogan de que voltei são e salvo?" />
    <String id="18105006" string="Acompanhe um pesquisador até a Estação Qeldar." />
    <String id="18105007" string="&quot;Fico feliz em ajudar.&quot;" />
    <String id="18105008" string="Fale com Rogand." />
</StrSheet_Quest>
