
<StrSheet_Quest xmlns="https://vezel.dev/novadrop/dc/StrSheet_Quest" xmlns:xsi="http://www.w3.org/2001/XMLSchema-instance" xsi:schemaLocation="https://vezel.dev/novadrop/dc/StrSheet_Quest StrSheet_Quest.xsd">
    <String id="60807001" string="Recursos Humanos" />
    <String id="60807002" string="Precisamos de corpos quentes, pura e simplesmente. Não se preocupe muito com o processo de entrevista." />
    <String id="60807003" string="Chame isso de taxa de indicação." />
    <String id="60807004" string="&quot;Basta ir até Loyek&quot;." />
    <String id="60807005" string="Encontre um vagabundo perto de Cutthroat Harbor." />
    <String id="60807006" string="&quot;O trabalho de Loyek pode não ir tão longe.&quot;" />
    <String id="60807007" string="Encontre um vagabundo perto de Cutthroat Harbor." />
    <String id="60807008" string="&quot;Sou totalmente a favor de encontrar empregos para as pessoas.&quot;" />
    <String id="60807009" string="Vá para Loyek." />
</StrSheet_Quest>
