<?xml version='1.0' encoding='utf-8'?>
<VillagerDialog xmlns="https://vezel.dev/novadrop/dc/VillagerDialog" xmlns:xsi="http://www.w3.org/2001/XMLSchema-instance" xsi:schemaLocation="https://vezel.dev/novadrop/dc/VillagerDialog VillagerDialog.xsd" huntingZoneId="122" id="30000" voiceTypeId="98">
    <Text id="1" endSocial="14">
         
        <Page social="4" voiceTypeId="0">The Enlightened Union is happy to assist its members with fair and equitable trading.</Page>
    
    </Text>
    <Text id="6" endSocial="4">
         
        <Page social="0" voiceTypeId="0">This is not for another alliance.</Page>
    
    </Text>
</VillagerDialog>