<StrSheet_Quest xmlns:xsi="http://www.w3.org/2001/XMLSchema-instance" xsi:schemaLocation="https://vezel.dev/novadrop/dc/StrSheet_Quest StrSheet_Quest.xsd" xmlns="https://vezel.dev/novadrop/dc/StrSheet_Quest">
    <String id="803001" string="The Long Goodbye" />
    <String id="803002" string="Read the rescue orders." />
    <String id="803003" string="Hennika!" />
    <String id="803004" string="Detrian" />
    <String id="803005" string="Tell Karina that Detrian is missing." />
    <String id="803006" string="Bring news about Hennika to Detrian at Avenger Outpost." />
    <String id="803007" string="&quot;I'll find him.&quot;" />
    <String id="803008" string="Check with Karina about Detrian's whereabouts." />
    <String id="803009" string="&quot;I won't.&quot;" />
    <String id="803010" string="Check with Loxetrius at Vanguard Post Alpha." />
    <String id="803011" string="Eliminate the gula skinners and slavering auric imps in the Hungry Caverns Catacombs." />
    <String id="803012" string="&quot;Return to the dream, my friend.&quot;" />
    <String id="803013" string="Search the half-eaten corpse." />
    <String id="803014" string="&quot;Back before you can blink.&quot;" />
    <String id="803015" string="Report back to Loxetrius at Vanguard Post Alpha." />
    <String id="803016" string="&quot;I'll check it out.&quot;" />
    <String id="803017" string="Report to Rendia at Vanguard Post Beta." />
    <String id="803018" string="Detrian" />
    <String id="803019" string="There's someone in the cell on the right. It's Detrian!" />
    <String id="803020" string="Find the first cell." />
    <String id="803021" string="&quot;I'll save her, Detrian. I promise.&quot;" />
    <String id="803022" string="Speak to Detrian." />
    <String id="803023" string="Detrian" />
    <String id="803024" string="Fight the aberrant gulons and rescue the abducted villagers from the second cell." />
    <String id="803025" string="Move on to the second cell." />
    <String id="803026" string="Eliminate the aberrant gulons in the Cavern of Tears." />
    <String id="803027" string="&quot;No time to talk. Run!&quot;" />
    <String id="803028" string="&quot;No time to talk. Run!&quot;" />
    <String id="803029" string="&quot;No time to talk. Run!&quot;" />
    <String id="803030" string="&quot;No time to talk. Run!&quot;" />
    <String id="803031" string="&quot;No time to talk. Run!&quot;" />
    <String id="803032" string="Free the abductees from their cell." />
    <String id="803033" string="&quot;I'll find his sword.&quot;" />
    <String id="803034" string="Speak with Hennika." />
    <String id="803035" string="Eliminate vulgar inquisitors in the Hungry Caverns Depths, and retrieve Detrian's sword." />
    <String id="803036" string="&quot;He'll be proud of you.&quot;" />
    <String id="803037" string="Deliver Detrian's sword to Hennika at Avenger Outpost." />
    <String id="803038" string="Deliver Detrian's sword to Hennika at Avenger Outpost." />
    <String id="803039" string="&quot;She's had to grow up fast.&quot;" />
    <String id="803040" string="Report to Karina." />
</StrSheet_Quest>
