<?xml version="1.0" encoding="utf-8"?>
<QuestDialog xmlns="https://vezel.dev/novadrop/dc/QuestDialog" xmlns:xsi="http://www.w3.org/2001/XMLSchema-instance" xsi:schemaLocation="https://vezel.dev/novadrop/dc/QuestDialog QuestDialog.xsd" huntingZoneId="608" id="7" voiceTypeId="0">
    <Text huntingZoneId="0" id="1" prevId="0" villagerId="0" />
    <Text huntingZoneId="62" id="100" prevId="0" villagerId="1705">
         
        <Page social="0" />
    
    </Text>
    <Text huntingZoneId="62" id="2" prevId="0" villagerId="1705">
         
        <Page social="4">Jax hires only the best. Our people are our best asset.&lt;BR&gt;&lt;BR&gt;And we need some help hiring...hiring workers who'll do anything for the organization, if you know what I mean. See what you can find around Cutthroat Harbor.</Page>
    
    </Text>
    <Text huntingZoneId="62" id="3" prevId="2" villagerId="1707">
         
        <Page social="4">A job with Jax?&lt;BR&gt;&lt;BR&gt;Beats starving. I'm in.</Page>
    
    </Text>
    <Text huntingZoneId="62" id="4" prevId="3" villagerId="1708">
         
        <Page social="4">Are you kidding? I'd kill for a job!</Page>
    
    </Text>
    <Text huntingZoneId="62" id="5" prevId="4" villagerId="1705">
         
        <Page social="4">For what we have in mind, those hobos are perfect.&lt;BR&gt;&lt;BR&gt;Take your reward, and remember: this is a labor-intensive industry. We always need more workers who'll do whatever it takes.</Page>
    
    </Text>
</QuestDialog>
