<QuestDialog xmlns:xsi="http://www.w3.org/2001/XMLSchema-instance" xsi:schemaLocation="https://vezel.dev/novadrop/dc/QuestDialog QuestDialog.xsd" id="24" huntingZoneId="27" voiceTypeId="0" xmlns="https://vezel.dev/novadrop/dc/QuestDialog">
    <Text id="1" huntingZoneId="0" prevId="0" villagerId="0" />
    <Text id="100" huntingZoneId="227" prevId="0" villagerId="1015">
        <Page social="0" />
    </Text>
    <Text id="2" huntingZoneId="227" prevId="0" villagerId="1015">
        <Page social="5">Castra Mysterium needs immediate resupply. {@LinkCreature:227#1020#Eerix} won't listen to me any more maybe he'll listen to you.&lt;BR&gt;&lt;BR&gt;Tell him we need those supplies!</Page>
    </Text>
    <Text id="3" huntingZoneId="227" prevId="2" villagerId="1020">
        <Page social="9">What? Get more supplies? Darn it! It’s over! Thulsa's troops took all of our supplies.&lt;BR&gt;&lt;BR&gt;There might be some left in the farmhouse, but {@LinkCreature:27#16$$Calapana} will have the rest.</Page>
    </Text>
    <Text id="4" huntingZoneId="227" prevId="3" villagerId="1020">
        <Page social="7">You've got a good eye for this sort of thing. If you're ever heading to Castanica, we could make a tidy profit.&lt;BR&gt;&lt;BR&gt;Let {@LinkCreature:227#1015#Ovellia} know the shipment's ready.</Page>
    </Text>
    <Text id="5" huntingZoneId="227" villagerId="1020">
        <Page social="0">You're poaching on my time. If you want something, hurry it up.</Page>
    </Text>
    <Text id="6" huntingZoneId="227" prevId="4" villagerId="1015">
        <Page social="5">Supply isn't the glorious side of the military, but it's arguably the most vital. Thank you for helping us get this shipment together.</Page>
    </Text>
</QuestDialog>
