<QuestDialog xmlns:xsi="http://www.w3.org/2001/XMLSchema-instance" xsi:schemaLocation="https://vezel.dev/novadrop/dc/QuestDialog QuestDialog.xsd" id="2" huntingZoneId="426" voiceTypeId="0" xmlns="https://vezel.dev/novadrop/dc/QuestDialog">
    <Text id="1" huntingZoneId="0" prevId="0" villagerId="0" />
    <Text id="100" huntingZoneId="426" prevId="0" villagerId="2003">
        <Page social="0" />
    </Text>
    <Text id="2" huntingZoneId="426" prevId="0" villagerId="2003">
        <Page social="0">(You find a scout report on the corpse. If other scouts came to Argon Corpus, they may have similar reports.)</Page>
    </Text>
    <Text id="3" huntingZoneId="426" prevId="2" villagerId="2004">
        <Page social="0">(You find a scout report on the corpse.)</Page>
    </Text>
    <Text id="4" huntingZoneId="426" prevId="3" villagerId="2006">
        <Page social="0">(You find a scout report on the corpse.)</Page>
    </Text>
    <Text id="5" huntingZoneId="426" prevId="4" villagerId="2005">
        <Page social="0">(You find a scout report. Unlike the other scouts, this one died in fetal position, as if trying to protect the report.)</Page>
    </Text>
    <Text id="6" huntingZoneId="76" prevId="5" villagerId="1020">
        <Page social="4">What's this? A report written by the rangers we sent...oh, no. They aren't coming back, are they?&lt;NEXTPAGEBUTTON&gt;"The argons used screams as weapons."&lt;/NEXTPAGEBUTTON&gt;</Page>
        <Page social="4">This is the essence of what killed them? Chilling.&lt;BR&gt;&lt;BR&gt;This may be useful to us, &lt;PCNAME&gt;.&lt;BR&gt;&lt;BR&gt;Perhaps we can use this essence to develop a countermeasure. Or maybe even use it as a weapon ourselves someday.</Page>
    </Text>
    <Text id="7" huntingZoneId="76" villagerId="1020">
        <Page social="0" />
    </Text>
</QuestDialog>
