
<StrSheet_Quest xmlns="https://vezel.dev/novadrop/dc/StrSheet_Quest" xmlns:xsi="http://www.w3.org/2001/XMLSchema-instance" xsi:schemaLocation="https://vezel.dev/novadrop/dc/StrSheet_Quest StrSheet_Quest.xsd">
    <String id="5502001" string="O espírito indomável" />
    <String id="5502002" string="Não devemos permitir que o sono de Sikander seja perturbado." />
    <String id="5502003" string="&quot;Estou cuidando disso.&quot;" />
    <String id="5502004" string="[Dragonfall] O prefeito Ghazi era um aliado leal do general Kanmur. Pergunte a ele sobre a missão de Kanmur." />
    <String id="5502005" string="&quot;Vivos ou mortos, eu os encontrarei.&quot;" />
    <String id="5502006" string="[Guarnição de Darkquaver] Encontre o Centurião Thaqib." />
    <String id="5502007" string="Leia o relatório." />
    <String id="5502008" string="Verifique o corpo do guarda morto." />
    <String id="5502009" string="Leia o relatório." />
    <String id="5502010" string="Você terminou de ler o relatório." />
    <String id="5502011" string="&quot;Vou até lá agora.&quot;" />
    <String id="5502012" string="[Posto Avançado de Valumnir] Traga o relatório que você recuperou para Rowin." />
    <String id="5502013" string="Encontre Rowin." />
    <String id="5502014" string="Equipe de Isren" />
    <String id="5502015" string="Ali estão os corpos dos guardas!" />
    <String id="5502016" string="[Equipe de Isren] Procure na área os guardas que viajaram com Neira." />
    <String id="5502017" string="&quot;Estou cuidando disso.&quot;" />
    <String id="5502018" string="Encontre e resgate Neira antes que seja tarde demais!" />
    <String id="5502019" string="Pelo despertar de Sikander!" />
    <String id="5502020" string="Sikander..." />
    <String id="5502021" string="Você não pode me impedir!" />
    <String id="5502022" string="Meu poder... não é suficiente." />
    <String id="5502023" string="Krawww!" />
    <String id="5502024" string="Gurrr..." />
    <String id="5502025" string="Elimine os sacerdotes que estão reforçando o Ishlangu." />
    <String id="5502026" string="Desativar o Ishlangu." />
    <String id="5502027" string="Informe ao Neira." />
    <String id="5502028" string="Desative o Ishlangu e liberte Isrenia." />
    <String id="5502029" string="&quot;Venha comigo.&quot;" />
    <String id="5502030" string="Fale com Isrenia." />
</StrSheet_Quest>
