<?xml version='1.0' encoding='utf-8'?>
<StrSheet_Quest xmlns="https://vezel.dev/novadrop/dc/StrSheet_Quest" xmlns:xsi="http://www.w3.org/2001/XMLSchema-instance" xsi:schemaLocation="https://vezel.dev/novadrop/dc/StrSheet_Quest StrSheet_Quest.xsd">
    <String id="60510001" string="Trabalho de Taratia" />
    <String id="60510002" string="&quot;Ok...&quot;" />
    <String id="60510003" string="" />
    <String id="60510004" string="" />
    <String id="60510005" string="Pergunte a {@LinkCreature:63#3002#Taratia} sobre o trabalho que ela tem para você." />
    <String id="60510006" string="&quot;Estou cuidando disso.&quot;" />
    <String id="60510007" string="&quot;Obrigado.&quot;" />
    <String id="60510008" string="Entregue a essência de raio ao guia de criação de Velika, {@LinkCreature:63#1098#Santia}." />
    <String id="60510009" string="" />
    <String id="60510010" string="&quot;Obrigado.&quot;" />
    <String id="60510011" string="Entregue o minério de xermetal ao guia de criação de Velika, {@LinkCreature:63#1098#Santia}." />
    <String id="60510012" string="" />
    <String id="60510013" string="&quot;Até a próxima vez&quot;." />
    <String id="60510014" string="Retorne a {@LinkCreature:63#3002#Taratia}." />
</StrSheet_Quest>