
<StrSheet_Quest xmlns="https://vezel.dev/novadrop/dc/StrSheet_Quest" xmlns:xsi="http://www.w3.org/2001/XMLSchema-instance" xsi:schemaLocation="https://vezel.dev/novadrop/dc/StrSheet_Quest StrSheet_Quest.xsd">
    <String id="1308001" string="Essência do presságio" />
    <String id="1308002" string="O que poderia afetar tanto uma espada quanto um espírito?" />
    <String id="1308003" string="Os espíritos são apenas um sintoma de um problema maior aqui." />
    <String id="1308004" string="Core Essence" />
    <String id="1308005" string="Obtenha as essências essenciais dos pesarosos andarilhos das espirais." />
    <String id="1308006" string="Traga as essências para Eria." />
    <String id="1308007" string="&quot;Eu entendo.&quot;" />
    <String id="1308008" string="&quot;Pela federação!&quot;" />
    <String id="1308009" string="Fale com Leander." />
</StrSheet_Quest>
